say_hello/__init__.py
say_hello/say_hello.py
say_hello_sample_library-0.1.2.dist-info/WHEEL
say_hello_sample_library-0.1.2.dist-info/METADATA
say_hello_sample_library-0.1.2.dist-info/RECORD
