Metadata-Version: 2.3
Name: say-hello-sample-library
Version: 0.1.2
Summary: A sample package
Author: CharlyGin
Author-email: CharlyGin <support@charly-ginevra.fr>
Requires-Python: >=3.9
